{
  "ad_id": "1240123894166496",
  "image_url": "https://scontent.fdac189-1.fna.fbcdn.net/v/t39.35426-6/506792913_982250680484373_7544006189937226286_n.jpg?stp=dst-jpg_s600x600_tt6&_nc_cat=109&ccb=1-7&_nc_sid=c53f8f&_nc_ohc=-VUZnEhy2-0Q7kNvwEviBU1&_nc_oc=AdnlgO_nBWeGlujO0UlF8r80X-H6eHeNTzWJKtreMBgGDMyYaGMto7PBPx1mm7_xcVA&_nc_zt=14&_nc_ht=scontent.fdac189-1.fna&_nc_gid=F4iinj08ATZkNewFBozIaw&oh=00_AfOXNHCKFlbKk3joGRnxWdWrk7u8egDWWRFKIYbmeXFrCA&oe=686D0472",
  "car_model": "Tesla Model Y",
  "advertiser_name": NaN,
  "page_name": "Local Deals",
  "ad_title": "A Guide About Tesla Model Y (juniper) 2025. Learn More",
  "start_date": "2025-06-16 08:00:00",
  "end_date": "2025-06-19 08:00:00",
  "download_date": "2025-07-07T21:14:29.279578",
  "image_size": [
    600,
    600
  ],
  "image_mode": "RGB",
  "file_size": 47840
}