{
  "ad_id": "1511853256445793",
  "image_url": "https://scontent.fruh6-1.fna.fbcdn.net/v/t39.35426-6/477389963_970655418507555_2216258202513490736_n.jpg?stp=dst-jpg_s600x600_tt6&_nc_cat=105&ccb=1-7&_nc_sid=c53f8f&_nc_ohc=nlzfAQ5WdvUQ7kNvwHQZb3M&_nc_oc=Adnqh2asl7MiCNL9J98kBHrdRSVD0HjAqwfymcXZJCHc34-T8NhkemYTrL_RrKvAJ_0&_nc_zt=14&_nc_ht=scontent.fruh6-1.fna&_nc_gid=koW1FsQZ9Z_2UDivB9hRNA&oh=00_AfMzKG9TE-2LgCvyR1G5SHmmRMnbZ62TpRoRjrAxNXnD-Q&oe=686D0688",
  "car_model": "Tesla Model Y",
  "advertiser_name": NaN,
  "page_name": "Gearhead Gazette",
  "ad_title": "\ud83d\ude97 A Guide for Tesla Model Y \ud83d\ude97",
  "start_date": "2025-02-10 09:00:00",
  "end_date": "2025-02-11 09:00:00",
  "download_date": "2025-07-07T21:21:54.177400",
  "image_size": [
    600,
    600
  ],
  "image_mode": "RGB",
  "file_size": 68624
}